README.rst
setup.py
tkinterhtml/__init__.py
tkinterhtml/__main__.py
tkinterhtml.egg-info/PKG-INFO
tkinterhtml.egg-info/SOURCES.txt
tkinterhtml.egg-info/dependency_links.txt
tkinterhtml.egg-info/top_level.txt
tkinterhtml/tkhtml/Linux/32-bit/Tkhtml/libTkhtml3.0.so
tkinterhtml/tkhtml/Linux/32-bit/Tkhtml/pkgIndex.tcl
tkinterhtml/tkhtml/Linux/64-bit/Tkhtml/libTkhtml3.0.so
tkinterhtml/tkhtml/Linux/64-bit/Tkhtml/pkgIndex.tcl
tkinterhtml/tkhtml/MacOSX/64-bit/Tkhtml/libTkhtml3.0.dylib
tkinterhtml/tkhtml/MacOSX/64-bit/Tkhtml/pkgIndex.tcl
tkinterhtml/tkhtml/Windows/32-bit/Tkhtml/Tkhtml30.dll
tkinterhtml/tkhtml/Windows/32-bit/Tkhtml/pkgIndex.tcl
tkinterhtml/tkhtml/Windows/64-bit/Tkhtml/Tkhtml30.dll
tkinterhtml/tkhtml/Windows/64-bit/Tkhtml/pkgIndex.tcl